shan_trans/__init__.py
shan_trans/shan_trans.py
shan_trans-0.0.1.dist-info/METADATA
shan_trans-0.0.1.dist-info/WHEEL
shan_trans-0.0.1.dist-info/licenses/LICENCE.txt
shan_trans-0.0.1.dist-info/RECORD
