Metadata-Version: 2.4
Name: shan_trans
Version: 0.0.1
Summary: A transcription tool for Shan (Tai) language
Author-email: Karl Seifen <seifenkarl@gmail.com>
License-Expression: MIT
License-File: LICENCE.txt
Classifier: Operating System :: OS Independent
Classifier: Programming Language :: Python :: 3
Requires-Python: >=3.9
